LICENCE
README.md
setup.py
selenium_network_intercept/__init__.py
selenium_network_intercept/intercept.py
selenium_network_intercept.egg-info/PKG-INFO
selenium_network_intercept.egg-info/SOURCES.txt
selenium_network_intercept.egg-info/dependency_links.txt
selenium_network_intercept.egg-info/top_level.txt
selenium_search_file/__init__.py
selenium_search_file/search_file.py