Metadata-Version: 2.1
Name: selenium-network-intercept
Version: 1.0.2
Summary: Interceptador de requisições http não oficial do selenium 4
Author: Alexandre Mariano
Author-email: alexandre_mariano@hotmail.com.br
License: MIT License
Keywords: selenium,network,intercept,http,requests,selenium network intercept,selenium intercept,search download selenium
License-File: LICENCE
